sc2Env/Sc2Bot.py
sc2Env/Sc2Env.py
sc2Env/__init__.py
sc2Env/action.py
sc2Env/bot_ai.py
sc2Env/cache.py
sc2Env/client.py
sc2Env/constants.py
sc2Env/controller.py
sc2Env/data.py
sc2Env/game_data.py
sc2Env/game_info.py
sc2Env/game_state.py
sc2Env/main.py
sc2Env/maps.py
sc2Env/paths.py
sc2Env/pixel_map.py
sc2Env/player.py
sc2Env/portconfig.py
sc2Env/position.py
sc2Env/power_source.py
sc2Env/protocol.py
sc2Env/renderer.py
sc2Env/sc2process.py
sc2Env/score.py
sc2Env/tmpfix.py
sc2Env/unit.py
sc2Env/unit_command.py
sc2Env/units.py
sc2Env/helpers/__init__.py
sc2Env/helpers/control_group.py
sc2Env/ids/__init__.py
sc2Env/ids/ability_id.py
sc2Env/ids/buff_id.py
sc2Env/ids/effect_id.py
sc2Env/ids/unit_typeid.py
sc2Env/ids/upgrade_id.py
sc2_env-0.11.1.2.dist-info/LICENSE
sc2_env-0.11.1.2.dist-info/METADATA
sc2_env-0.11.1.2.dist-info/WHEEL
sc2_env-0.11.1.2.dist-info/top_level.txt
sc2_env-0.11.1.2.dist-info/RECORD
